LICENSE
setup.py
helloxl/__init__.py
helloxl/main.py
helloxl.egg-info/PKG-INFO
helloxl.egg-info/SOURCES.txt
helloxl.egg-info/dependency_links.txt
helloxl.egg-info/top_level.txt