Metadata-Version: 2.1
Name: helloxl
Version: 0.1.4
Summary: Pytorch-lightning Code Blocks for NLP
Home-page: https://github.com/xulang/test_xl
Author: xulang
Author-email: 1659821119@qq.com
License: MIT Licence
Platform: UNKNOWN
Requires-Python: >=3.8
License-File: LICENSE
